MANIFEST.in
README.md
requirements.txt
setup.cfg
setup.py
md_mqtt/__init__.py
md_mqtt/config.schema.yml
md_mqtt/server.py
md_mqtt.egg-info/PKG-INFO
md_mqtt.egg-info/SOURCES.txt
md_mqtt.egg-info/dependency_links.txt
md_mqtt.egg-info/entry_points.txt
md_mqtt.egg-info/not-zip-safe
md_mqtt.egg-info/requires.txt
md_mqtt.egg-info/top_level.txt