Metadata-Version: 1.1
Name: md-mqtt
Version: 0.0.1
Summary: Publish Linux MD RAID status to MQTT
Home-page: https://github.com/flyte/md-mqtt
Author: Ellis Percival
Author-email: md_mqtt@failcode.co.uk
License: MIT
Platform: UNKNOWN
Classifier: Programming Language :: Python
Classifier: Intended Audience :: Developers
Classifier: License :: OSI Approved :: MIT License
Classifier: Natural Language :: English
Classifier: Operating System :: OS Independent
Classifier: Topic :: Communications
Classifier: Topic :: Home Automation
Classifier: Topic :: System :: Networking
